ecs_connect/__init__.py
ecs_connect/cli.py
ecs_connect/config.py
ecs_connect/ecs.py
ecs_connect/ssm.py
ecs_connect/version.py
ecs_connect-3.2.2.dist-info/AUTHORS.rst
ecs_connect-3.2.2.dist-info/LICENSE
ecs_connect-3.2.2.dist-info/METADATA
ecs_connect-3.2.2.dist-info/WHEEL
ecs_connect-3.2.2.dist-info/entry_points.txt
ecs_connect-3.2.2.dist-info/top_level.txt
ecs_connect-3.2.2.dist-info/RECORD
