Metadata-Version: 2.1
Name: ecs-connect
Version: 3.2.2
Summary: Seamlessly connect to containers running in ECS.
Home-page: https://github.com/saurabhjambhule/ecs_connect
Author: Saurabh Jambhule
Author-email: saurabhjambhule@gmail.com
License: MIT license
Keywords: ecs_connect,ecs
Platform: UNKNOWN
Classifier: Intended Audience :: Developers
Classifier: License :: OSI Approved :: MIT License
Classifier: Natural Language :: English
Classifier: Programming Language :: Python :: 3
Classifier: Programming Language :: Python :: 3.5
Classifier: Programming Language :: Python :: 3.6
Classifier: Programming Language :: Python :: 3.7
Classifier: Programming Language :: Python :: 3.8
Requires-Python: >=3.5
License-File: LICENSE
License-File: AUTHORS.rst
Requires-Dist: click (>=7.0)
Requires-Dist: boto3 (>=1.16.9)
Requires-Dist: botocore (>=1.19.9)
Requires-Dist: ConfigParser (>=4.0.2)
Requires-Dist: websockets (>=8.1)
Requires-Dist: inquirer (>=2.10.0)
